unbound_report/__init__.py
unbound_report/extract_data.py
unbound_report/generate_report.py
unbound_report/templates/report.html
unbound_report-1.0.1.dist-info/LICENSE
unbound_report-1.0.1.dist-info/METADATA
unbound_report-1.0.1.dist-info/WHEEL
unbound_report-1.0.1.dist-info/entry_points.txt
unbound_report-1.0.1.dist-info/top_level.txt
unbound_report-1.0.1.dist-info/RECORD
