Metadata-Version: 2.1
Name: unbound-report
Version: 1.0.1
Summary: A tool to extract test suite data from Robot Framework output.xml and generate HTML reports.
Home-page: https://github.com/prasad0275/unbound-report.git
Author: Prasad Sawant
Author-email: sawant.prasad0275@gmail.com
Classifier: Programming Language :: Python :: 3
Classifier: License :: OSI Approved :: MIT License
Classifier: Operating System :: OS Independent
Requires-Python: >=3.10
License-File: LICENSE
Requires-Dist: robotframework
Requires-Dist: Jinja2 >=3.1.4
